{
   "agent": "Single core Echo",
   "behavior": "OK",
   "behaviorClose": "OK",
   "case": 389,
   "closedByMe": true,
   "createStats": true,
   "createWirelog": true,
   "description": "Send 1000 compressed messages each of payload size 131072, auto-fragment to 1024 octets. Use default permessage-deflate offer.",
   "droppedByMe": false,
   "duration": 37531,
   "expectation": "Receive echo'ed messages (with payload as sent). Timeout case after 480 secs.",
   "expected": {},
   "expectedClose": {
      "closeCode": [
         1000
      ],
      "closedByMe": true,
      "requireClean": true
   },
   "failedByMe": false,
   "httpRequest": "GET / HTTP/1.1\r\nUser-Agent: AutobahnTestSuite/0.8.1-0.10.9\r\nHost: 127.0.0.1:9001\r\nUpgrade: WebSocket\r\nConnection: Upgrade\r\nPragma: no-cache\r\nCache-Control: no-cache\r\nSec-WebSocket-Key: k73TnXaJio7ianci53wGeQ==\r\nSec-WebSocket-Extensions: permessage-deflate; client_no_context_takeover; client_max_window_bits\r\nSec-WebSocket-Version: 13\r\n\r\n",
   "httpResponse": "HTTP/1.1 101 Web Socket Protocol Handshake\r\nUpgrade: WebSocket\r\nConnection: Upgrade\r\nSec-WebSocket-Accept: uMwLxwx/BtlG2ON1GUe8y5h6EmI=\r\nSec-WebSocket-Extensions: permessage-deflate;client_max_window_bits=15;client_no_context_takeover\r\n\r\n",
   "id": "12.5.16",
   "isServer": false,
   "localCloseCode": 1000,
   "localCloseReason": null,
   "received": [],
   "remoteCloseCode": 1000,
   "remoteCloseReason": null,
   "reportCompressionRatio": true,
   "reportTime": true,
   "result": "Ok, received all echo'ed messages in time.",
   "resultClose": "Connection was properly closed",
   "rxFrameStats": {
      "0": 5480,
      "2": 1000,
      "8": 1
   },
   "rxOctetStats": {
      "4": 1,
      "16": 12,
      "238": 1,
      "439": 1,
      "515": 1,
      "522": 1,
      "741": 1,
      "902": 1,
      "1263": 1,
      "1474": 1,
      "1565": 1,
      "1832": 1,
      "2008": 1,
      "2064": 1,
      "2717": 1,
      "2763": 1,
      "2764": 1,
      "2765": 1,
      "2816": 1,
      "2832": 1,
      "2905": 1,
      "3005": 1,
      "3628": 1,
      "3684": 1,
      "3939": 1,
      "4029": 1,
      "4084": 1,
      "4104": 3,
      "4116": 1,
      "4218": 1,
      "4226": 1,
      "4334": 1,
      "4368": 1,
      "4566": 2,
      "4584": 1,
      "4718": 1,
      "4811": 1,
      "4826": 1,
      "4866": 1,
      "4876": 1,
      "4940": 1,
      "4946": 1,
      "5057": 1,
      "5073": 1,
      "5095": 1,
      "5155": 1,
      "5194": 1,
      "5204": 1,
      "5240": 1,
      "5244": 1,
      "5387": 1,
      "5533": 1,
      "5702": 1,
      "5802": 1,
      "5915": 1,
      "5987": 1,
      "6009": 1,
      "6454": 1,
      "6485": 1,
      "6569": 1,
      "6645": 1,
      "6700": 1,
      "6803": 1,
      "6811": 1,
      "6832": 1,
      "7037": 1,
      "7055": 1,
      "7071": 1,
      "7129": 1,
      "7150": 1,
      "7327": 1,
      "7518": 1,
      "7598": 1,
      "7600": 1,
      "7805": 1,
      "8200": 1,
      "8413": 1,
      "8452": 1,
      "8481": 1,
      "8690": 1,
      "8771": 1,
      "8902": 1,
      "8972": 1,
      "8993": 1,
      "9096": 1,
      "9112": 1,
      "9188": 1,
      "9240": 1,
      "9353": 1,
      "9402": 1,
      "9425": 1,
      "9775": 1,
      "10019": 1,
      "10132": 1,
      "10136": 1,
      "10165": 1,
      "10201": 1,
      "10227": 1,
      "10279": 1,
      "10293": 1,
      "10297": 1,
      "10317": 1,
      "10321": 1,
      "10377": 1,
      "10396": 1,
      "10438": 1,
      "10439": 1,
      "10442": 1,
      "10572": 1,
      "10634": 1,
      "10656": 1,
      "10663": 1,
      "10664": 1,
      "10665": 1,
      "10677": 1,
      "10679": 1,
      "10684": 1,
      "10685": 1,
      "10690": 1,
      "10737": 1,
      "10740": 1,
      "10768": 1,
      "10780": 1,
      "10813": 1,
      "10865": 1,
      "10888": 1,
      "10895": 1,
      "10896": 1,
      "10900": 1,
      "10905": 1,
      "10909": 1,
      "10913": 1,
      "10915": 1,
      "10924": 1,
      "10941": 1,
      "10970": 1,
      "11027": 2,
      "11061": 1,
      "11077": 1,
      "11082": 1,
      "11083": 1,
      "11135": 1,
      "11137": 1,
      "11151": 1,
      "11152": 1,
      "11162": 1,
      "11170": 1,
      "11174": 1,
      "11175": 1,
      "11180": 1,
      "11204": 1,
      "11207": 1,
      "11233": 1,
      "11236": 1,
      "11240": 1,
      "11241": 1,
      "11245": 1,
      "11297": 1,
      "11337": 1,
      "11375": 1,
      "11405": 2,
      "11410": 1,
      "11413": 1,
      "11416": 1,
      "11569": 1,
      "11571": 1,
      "11727": 1,
      "11733": 1,
      "11734": 1,
      "11739": 1,
      "11741": 1,
      "11748": 1,
      "11949": 1,
      "11953": 1,
      "11966": 1,
      "11970": 1,
      "11985": 1,
      "11989": 1,
      "12033": 1,
      "12064": 1,
      "12128": 1,
      "12191": 1,
      "12210": 1,
      "12218": 1,
      "12268": 1,
      "12287": 1,
      "12291": 1,
      "12296": 1,
      "12316": 1,
      "12362": 1,
      "12373": 1,
      "12381": 1,
      "12425": 1,
      "12435": 1,
      "12510": 1,
      "12511": 1,
      "12521": 1,
      "12524": 1,
      "12526": 1,
      "12530": 1,
      "12543": 1,
      "12566": 1,
      "12568": 1,
      "12592": 1,
      "12593": 1,
      "12606": 1,
      "12640": 1,
      "12642": 1,
      "12644": 1,
      "12650": 1,
      "12655": 1,
      "12658": 1,
      "12671": 1,
      "12804": 1,
      "12809": 1,
      "12811": 1,
      "12854": 1,
      "12951": 1,
      "12982": 1,
      "12984": 2,
      "12999": 1,
      "13016": 1,
      "13052": 1,
      "13053": 1,
      "13066": 1,
      "13086": 1,
      "13152": 1,
      "13170": 1,
      "13182": 1,
      "13265": 1,
      "13292": 1,
      "13321": 1,
      "13358": 1,
      "13418": 1,
      "13475": 1,
      "13481": 1,
      "13485": 1,
      "13487": 1,
      "13503": 1,
      "13508": 2,
      "13509": 1,
      "13511": 1,
      "13527": 1,
      "13538": 1,
      "13553": 1,
      "13564": 1,
      "13565": 1,
      "13570": 1,
      "13571": 1,
      "13581": 1,
      "13582": 1,
      "13585": 1,
      "13587": 1,
      "13621": 1,
      "13624": 1,
      "13628": 1,
      "13671": 1,
      "13674": 1,
      "13680": 1,
      "13684": 1,
      "13719": 1,
      "13724": 1,
      "13726": 1,
      "13734": 1,
      "13741": 1,
      "13763": 1,
      "13888": 1,
      "13919": 1,
      "13940": 1,
      "13947": 1,
      "13956": 1,
      "13967": 1,
      "14070": 1,
      "14093": 1,
      "14094": 1,
      "14290": 1,
      "14298": 1,
      "14941": 1,
      "15198": 1,
      "15263": 1,
      "15302": 1,
      "15324": 1,
      "15326": 1,
      "15387": 1,
      "15511": 1,
      "15541": 1,
      "15575": 1,
      "15638": 1,
      "15658": 1,
      "15687": 1,
      "15786": 1,
      "15788": 1,
      "15832": 1,
      "16019": 1,
      "16167": 1,
      "16192": 1,
      "16220": 1,
      "16270": 1,
      "16388": 10,
      "16392": 1,
      "16404": 7,
      "16452": 1,
      "16518": 1,
      "16844": 1,
      "16999": 1,
      "17353": 1,
      "17447": 1,
      "17496": 1,
      "17727": 1,
      "17787": 1,
      "17851": 1,
      "18033": 1,
      "18059": 1,
      "18270": 1,
      "18339": 1,
      "18394": 1,
      "18409": 1,
      "18683": 1,
      "19010": 1,
      "19140": 1,
      "19187": 1,
      "19365": 1,
      "19401": 1,
      "19407": 1,
      "19416": 1,
      "19643": 1,
      "19833": 1,
      "19847": 1,
      "19919": 1,
      "19974": 1,
      "20050": 1,
      "20086": 1,
      "20088": 1,
      "20209": 1,
      "20258": 1,
      "20484": 1,
      "20703": 1,
      "20758": 1,
      "21019": 1,
      "21045": 1,
      "21088": 1,
      "21156": 1,
      "21315": 1,
      "21325": 1,
      "21385": 1,
      "21395": 1,
      "21526": 1,
      "21536": 1,
      "21591": 1,
      "21614": 1,
      "21672": 1,
      "22097": 1,
      "22194": 1,
      "22273": 1,
      "22345": 1,
      "22348": 1,
      "22370": 1,
      "22404": 1,
      "22432": 1,
      "22509": 1,
      "22511": 1,
      "22527": 1,
      "22595": 1,
      "22599": 1,
      "22602": 1,
      "22659": 1,
      "22776": 1,
      "22790": 1,
      "22952": 1,
      "22969": 1,
      "23004": 1,
      "23020": 1,
      "23138": 1,
      "23407": 1,
      "23498": 1,
      "23571": 1,
      "23945": 1,
      "24082": 1,
      "24274": 1,
      "24584": 1,
      "25406": 1,
      "25466": 1,
      "25855": 1,
      "25861": 1,
      "26020": 1,
      "26109": 1,
      "26110": 1,
      "26282": 1,
      "26375": 1,
      "26474": 1,
      "26506": 1,
      "26511": 1,
      "26554": 1,
      "26575": 1,
      "26579": 1,
      "26645": 1,
      "26678": 1,
      "26700": 1,
      "26760": 1,
      "26828": 1,
      "26829": 2,
      "26830": 1,
      "26958": 1,
      "27021": 1,
      "27025": 1,
      "27055": 1,
      "27058": 1,
      "27070": 1,
      "27071": 1,
      "27072": 2,
      "27112": 1,
      "27120": 1,
      "27133": 1,
      "27147": 1,
      "27167": 1,
      "27185": 1,
      "27201": 1,
      "27251": 1,
      "27288": 1,
      "27290": 1,
      "27291": 2,
      "27292": 1,
      "27293": 1,
      "27335": 1,
      "27337": 1,
      "27356": 1,
      "27415": 1,
      "27418": 1,
      "27423": 1,
      "27456": 1,
      "27467": 1,
      "27471": 1,
      "27512": 1,
      "27526": 1,
      "27529": 1,
      "27541": 1,
      "27560": 1,
      "27563": 1,
      "27574": 1,
      "27590": 1,
      "27595": 1,
      "27596": 1,
      "27613": 1,
      "27616": 1,
      "27628": 1,
      "27694": 1,
      "27708": 1,
      "27713": 1,
      "27794": 1,
      "27803": 2,
      "27804": 1,
      "28004": 1,
      "28092": 1,
      "28113": 1,
      "28120": 1,
      "28127": 1,
      "28320": 1,
      "28336": 1,
      "28362": 1,
      "28370": 1,
      "28436": 1,
      "28466": 1,
      "28603": 1,
      "28640": 1,
      "28675": 1,
      "28699": 1,
      "28710": 1,
      "28716": 1,
      "28798": 1,
      "28811": 1,
      "28823": 1,
      "28874": 1,
      "28898": 1,
      "28995": 1,
      "28998": 1,
      "29005": 1,
      "29014": 1,
      "29031": 1,
      "29032": 1,
      "29037": 1,
      "29048": 1,
      "29065": 2,
      "29097": 1,
      "29153": 1,
      "29155": 1,
      "29200": 1,
      "29366": 1,
      "29393": 1,
      "29448": 1,
      "29519": 1,
      "29568": 1,
      "29648": 1,
      "29689": 1,
      "29711": 1,
      "29721": 1,
      "29737": 1,
      "29740": 1,
      "29798": 1,
      "29807": 1,
      "29810": 1,
      "29814": 1,
      "29829": 1,
      "29881": 1,
      "29953": 1,
      "29971": 1,
      "29979": 1,
      "30004": 1,
      "30006": 1,
      "30024": 1,
      "30052": 1,
      "30077": 1,
      "31355": 1,
      "31480": 1,
      "31578": 1,
      "31607": 1,
      "31609": 1,
      "31633": 1,
      "31678": 1,
      "31688": 1,
      "31740": 1,
      "31812": 1,
      "31914": 1,
      "32028": 1,
      "32063": 1,
      "32226": 1,
      "32295": 1,
      "32298": 1,
      "32385": 1,
      "32426": 1,
      "32478": 1,
      "32551": 1,
      "32580": 1,
      "32581": 1,
      "32629": 1,
      "32772": 1,
      "32776": 187,
      "32792": 4,
      "32928": 1,
      "33031": 1,
      "33112": 1,
      "33139": 1,
      "33586": 1,
      "33642": 1,
      "33681": 1,
      "33770": 1,
      "33786": 1,
      "33864": 1,
      "33979": 1,
      "34032": 1,
      "34098": 1,
      "35187": 1,
      "35591": 1,
      "35721": 1,
      "35804": 1,
      "35851": 1,
      "36129": 1,
      "36206": 1,
      "36249": 1,
      "36304": 1,
      "36339": 1,
      "36352": 2,
      "36382": 1,
      "36388": 1,
      "36451": 1,
      "36537": 1,
      "36628": 1,
      "36872": 9,
      "36936": 1,
      "37015": 1,
      "37046": 1,
      "37228": 1,
      "37265": 1,
      "37520": 1,
      "37710": 1,
      "37773": 1,
      "37782": 1,
      "37820": 1,
      "38718": 1,
      "38772": 1,
      "38817": 1,
      "38855": 1,
      "38864": 1,
      "38940": 1,
      "39076": 1,
      "39120": 1,
      "39128": 1,
      "39269": 1,
      "39295": 1,
      "39316": 1,
      "39322": 1,
      "39355": 1,
      "39622": 1,
      "39735": 1,
      "39808": 1,
      "39886": 1,
      "39959": 1,
      "40066": 1,
      "40083": 1,
      "40202": 1,
      "40353": 1,
      "40361": 1,
      "40362": 1,
      "40390": 1,
      "40469": 1,
      "40569": 1,
      "40964": 1,
      "40968": 10,
      "41685": 1,
      "41742": 1,
      "41841": 1,
      "41941": 1,
      "42039": 1,
      "42042": 1,
      "42043": 1,
      "42351": 1,
      "42625": 1,
      "42979": 1,
      "43046": 1,
      "43049": 1,
      "43189": 1,
      "43201": 1,
      "43316": 1,
      "43328": 1,
      "43676": 1,
      "43831": 1,
      "43907": 1,
      "43978": 1,
      "43981": 1,
      "44020": 1,
      "44147": 1,
      "44167": 1,
      "44624": 1,
      "44731": 1,
      "44860": 1,
      "44984": 1,
      "45006": 1,
      "45050": 1,
      "45060": 1,
      "45064": 10,
      "45076": 1,
      "45111": 1,
      "45153": 1,
      "45180": 1,
      "45214": 1,
      "45229": 1,
      "45231": 1,
      "45269": 1,
      "45270": 1,
      "45302": 1,
      "45370": 1,
      "45428": 1,
      "45430": 1,
      "45440": 1,
      "45497": 1,
      "45569": 1,
      "45696": 1,
      "45735": 1,
      "45941": 1,
      "46173": 1,
      "46371": 1,
      "46453": 1,
      "46484": 1,
      "46537": 1,
      "46541": 1,
      "46548": 1,
      "46551": 1,
      "47057": 1,
      "47379": 1,
      "47412": 1,
      "47414": 1,
      "47423": 1,
      "47526": 1,
      "47646": 1,
      "47843": 1,
      "47865": 1,
      "47973": 1,
      "48085": 1,
      "48103": 1,
      "48199": 1,
      "48216": 1,
      "48247": 1,
      "48311": 1,
      "48313": 1,
      "48351": 1,
      "48374": 1,
      "48398": 1,
      "48633": 1,
      "48677": 1,
      "48882": 1,
      "49135": 1,
      "49156": 1,
      "49160": 10,
      "49164": 242,
      "49180": 9,
      "50184": 1,
      "50365": 1,
      "50538": 1,
      "50554": 1,
      "50632": 1,
      "50678": 1,
      "50942": 1,
      "50956": 1,
      "51008": 1,
      "51173": 1,
      "51186": 1,
      "51223": 1,
      "51264": 1,
      "51302": 1,
      "51343": 1,
      "51365": 1,
      "51539": 1,
      "51885": 1,
      "52144": 1,
      "52233": 1,
      "52929": 1,
      "53256": 4,
      "53260": 1,
      "53405": 1,
      "53446": 1,
      "53494": 1,
      "53527": 1,
      "53662": 1,
      "53990": 1,
      "54053": 1,
      "54266": 1,
      "54267": 1,
      "54341": 1,
      "54379": 1,
      "54948": 1,
      "54968": 1,
      "55048": 1,
      "55195": 1,
      "55288": 1,
      "55361": 1,
      "55386": 1,
      "55451": 1,
      "55464": 1,
      "55560": 1,
      "55608": 1,
      "55630": 1,
      "55722": 1,
      "55848": 1,
      "56110": 1,
      "56720": 1,
      "56738": 1,
      "57352": 5,
      "57356": 5,
      "57616": 1,
      "57754": 1,
      "58020": 1,
      "58026": 1,
      "58156": 1,
      "58448": 1,
      "58479": 1,
      "58496": 1,
      "58508": 1,
      "58621": 1,
      "59002": 1,
      "59067": 1,
      "59132": 1,
      "59197": 1,
      "59368": 1,
      "59453": 1,
      "59457": 1,
      "59461": 2,
      "59584": 1,
      "59595": 1,
      "59605": 2,
      "59611": 1,
      "59683": 1,
      "59725": 1,
      "59734": 1,
      "59738": 1,
      "59743": 1,
      "59748": 1,
      "59793": 1,
      "59795": 1,
      "59799": 1,
      "59814": 1,
      "59829": 1,
      "59831": 1,
      "59832": 1,
      "59838": 1,
      "59840": 1,
      "59844": 2,
      "59846": 1,
      "59849": 1,
      "59851": 1,
      "59855": 2,
      "59894": 1,
      "59897": 1,
      "59900": 1,
      "59901": 1,
      "59902": 1,
      "59905": 1,
      "59945": 1,
      "59948": 1,
      "59975": 1,
      "60008": 1,
      "60029": 1,
      "60051": 1,
      "60060": 2,
      "60066": 1,
      "60070": 2,
      "60080": 1,
      "60082": 1,
      "60103": 1,
      "60111": 1,
      "60113": 1,
      "60126": 1,
      "60131": 1,
      "60134": 1,
      "60137": 1,
      "60173": 1,
      "60176": 1,
      "60196": 1,
      "60198": 1,
      "60203": 2,
      "60229": 1,
      "60233": 1,
      "60235": 1,
      "60242": 1,
      "60245": 1,
      "60256": 1,
      "60300": 1,
      "60306": 1,
      "60322": 1,
      "60329": 2,
      "60333": 1,
      "60339": 1,
      "60359": 1,
      "60366": 1,
      "60369": 1,
      "60371": 1,
      "60393": 2,
      "60395": 1,
      "60398": 1,
      "60399": 1,
      "60400": 3,
      "60405": 1,
      "60406": 1,
      "60435": 1,
      "60475": 1,
      "60478": 1,
      "60487": 1,
      "60499": 1,
      "60642": 1,
      "60731": 1,
      "60732": 1,
      "60733": 1,
      "60739": 1,
      "60897": 1,
      "60899": 1,
      "60901": 1,
      "61013": 1,
      "61093": 1,
      "61116": 1,
      "61117": 1,
      "61120": 1,
      "61121": 1,
      "61132": 1,
      "61134": 1,
      "61135": 1,
      "61140": 1,
      "61142": 1,
      "61145": 1,
      "61148": 1,
      "61149": 1,
      "61150": 1,
      "61189": 1,
      "61199": 1,
      "61202": 1,
      "61222": 1,
      "61227": 1,
      "61254": 1,
      "61372": 1,
      "61377": 1,
      "61379": 1,
      "61386": 1,
      "61429": 1,
      "61436": 1,
      "61437": 1,
      "61446": 1,
      "61448": 6,
      "61452": 1,
      "61463": 1,
      "61482": 1,
      "61517": 1,
      "61595": 1,
      "61597": 1,
      "61672": 1,
      "61680": 1,
      "61681": 1,
      "61691": 1,
      "61698": 1,
      "61728": 1,
      "61729": 1,
      "61731": 1,
      "61733": 1,
      "61766": 1,
      "61777": 1,
      "61778": 1,
      "61779": 2,
      "61781": 1,
      "61785": 1,
      "61788": 1,
      "61797": 1,
      "61804": 2,
      "61806": 1,
      "61807": 1,
      "61811": 1,
      "61813": 1,
      "61825": 1,
      "61830": 1,
      "61834": 2,
      "61925": 1,
      "61931": 1,
      "61935": 1,
      "61951": 1,
      "61972": 1,
      "61973": 1,
      "61976": 1,
      "61981": 1,
      "62093": 1,
      "62113": 1,
      "62117": 1,
      "62140": 1,
      "62141": 1,
      "62143": 1,
      "62180": 1,
      "62198": 1,
      "62199": 1,
      "62210": 1,
      "62217": 1,
      "62297": 1,
      "62343": 1,
      "62348": 1,
      "62440": 1,
      "62448": 2,
      "62453": 1,
      "62462": 1,
      "62471": 1,
      "62505": 1,
      "62506": 1,
      "62507": 1,
      "62515": 1,
      "62567": 1,
      "62576": 1,
      "62577": 1,
      "62586": 2,
      "62590": 1,
      "62595": 1,
      "62630": 1,
      "62635": 1,
      "62640": 1,
      "62646": 1,
      "62649": 1,
      "62650": 1,
      "62651": 1,
      "62653": 1,
      "62659": 1,
      "62698": 1,
      "62700": 1,
      "62701": 1,
      "62703": 1,
      "62731": 2,
      "62733": 1,
      "62734": 1,
      "62742": 1,
      "62756": 1,
      "62758": 1,
      "62779": 1,
      "62783": 1,
      "62836": 1,
      "62851": 1,
      "62859": 2,
      "62891": 1,
      "62894": 1,
      "62895": 1,
      "62897": 1,
      "62907": 1,
      "62983": 1,
      "63100": 1,
      "63106": 1,
      "63118": 1,
      "63121": 1,
      "63122": 1,
      "63234": 1,
      "63250": 1,
      "63256": 1,
      "64441": 1,
      "64481": 1,
      "64560": 1,
      "64677": 1,
      "64780": 1,
      "64835": 1,
      "64886": 1,
      "64988": 1,
      "65311": 1,
      "65536": 664
   },
   "started": "2019-12-28T17:43:19.769Z",
   "trafficStats": {
      "incomingCompressionRatio": 0.763370231628418,
      "incomingOctetsAppLevel": 131072000,
      "incomingOctetsWebSocketLevel": 100056463,
      "incomingOctetsWireLevel": 100082381,
      "incomingWebSocketFrames": 6480,
      "incomingWebSocketMessages": 1000,
      "incomingWebSocketOverhead": 0.0002590337417783797,
      "outgoingCompressionRatio": 0.763370231628418,
      "outgoingOctetsAppLevel": 131072000,
      "outgoingOctetsWebSocketLevel": 100056463,
      "outgoingOctetsWireLevel": 100841907,
      "outgoingWebSocketFrames": 98210,
      "outgoingWebSocketMessages": 1000,
      "outgoingWebSocketOverhead": 0.007850007650180478,
      "preopenIncomingOctetsWireLevel": 238,
      "preopenOutgoingOctetsWireLevel": 338
   },
   "txFrameStats": {
      "0": 97210,
      "2": 1000,
      "8": 1
   },
   "txOctetStats": {
      "8": 1,
      "9": 2,
      "10": 2,
      "11": 1,
      "13": 3,
      "14": 3,
      "15": 1,
      "16": 1,
      "17": 2,
      "18": 1,
      "20": 2,
      "21": 2,
      "22": 1,
      "23": 1,
      "25": 2,
      "26": 1,
      "29": 1,
      "32": 3,
      "33": 1,
      "35": 2,
      "36": 2,
      "38": 1,
      "39": 3,
      "42": 2,
      "43": 3,
      "44": 1,
      "45": 1,
      "47": 1,
      "48": 1,
      "49": 3,
      "50": 1,
      "51": 1,
      "52": 1,
      "53": 2,
      "54": 1,
      "55": 1,
      "56": 1,
      "57": 1,
      "59": 1,
      "60": 2,
      "62": 1,
      "65": 1,
      "66": 1,
      "70": 3,
      "71": 1,
      "74": 1,
      "75": 2,
      "77": 1,
      "79": 1,
      "80": 1,
      "82": 1,
      "83": 1,
      "84": 1,
      "85": 1,
      "86": 1,
      "87": 2,
      "91": 1,
      "92": 3,
      "93": 1,
      "96": 3,
      "97": 1,
      "100": 2,
      "101": 1,
      "102": 1,
      "105": 1,
      "108": 1,
      "109": 1,
      "110": 1,
      "113": 3,
      "116": 1,
      "118": 2,
      "120": 1,
      "123": 2,
      "124": 1,
      "126": 1,
      "127": 2,
      "129": 3,
      "130": 1,
      "131": 2,
      "134": 2,
      "135": 3,
      "137": 1,
      "139": 3,
      "140": 2,
      "141": 1,
      "142": 1,
      "143": 1,
      "144": 2,
      "146": 1,
      "147": 2,
      "149": 1,
      "151": 1,
      "152": 2,
      "154": 1,
      "155": 2,
      "157": 3,
      "158": 1,
      "160": 1,
      "161": 2,
      "162": 2,
      "163": 3,
      "165": 1,
      "167": 1,
      "168": 1,
      "169": 3,
      "170": 1,
      "177": 1,
      "179": 3,
      "181": 2,
      "183": 1,
      "184": 3,
      "185": 1,
      "186": 2,
      "187": 3,
      "188": 1,
      "189": 4,
      "190": 4,
      "195": 1,
      "197": 1,
      "203": 2,
      "204": 1,
      "205": 1,
      "207": 1,
      "208": 1,
      "209": 1,
      "210": 3,
      "211": 1,
      "212": 2,
      "213": 1,
      "214": 1,
      "215": 1,
      "216": 1,
      "217": 2,
      "218": 1,
      "219": 1,
      "221": 1,
      "224": 1,
      "226": 1,
      "227": 2,
      "229": 1,
      "230": 1,
      "232": 1,
      "234": 1,
      "236": 1,
      "238": 2,
      "239": 1,
      "240": 2,
      "242": 3,
      "243": 1,
      "244": 1,
      "245": 2,
      "246": 3,
      "251": 1,
      "257": 3,
      "258": 1,
      "259": 4,
      "260": 1,
      "261": 2,
      "262": 1,
      "263": 2,
      "264": 2,
      "265": 1,
      "266": 3,
      "267": 3,
      "268": 3,
      "269": 1,
      "270": 2,
      "271": 4,
      "276": 1,
      "278": 1,
      "285": 1,
      "286": 1,
      "291": 2,
      "292": 2,
      "293": 3,
      "294": 1,
      "295": 2,
      "297": 1,
      "298": 1,
      "299": 1,
      "300": 2,
      "302": 2,
      "304": 3,
      "306": 2,
      "307": 1,
      "308": 1,
      "309": 1,
      "310": 2,
      "313": 1,
      "314": 1,
      "315": 4,
      "316": 1,
      "317": 2,
      "318": 2,
      "319": 2,
      "320": 1,
      "321": 1,
      "322": 1,
      "324": 1,
      "325": 1,
      "326": 1,
      "327": 1,
      "328": 1,
      "331": 2,
      "332": 1,
      "333": 1,
      "338": 2,
      "340": 4,
      "342": 3,
      "343": 2,
      "344": 2,
      "345": 1,
      "347": 2,
      "348": 1,
      "349": 2,
      "350": 2,
      "353": 1,
      "354": 2,
      "355": 1,
      "356": 3,
      "358": 1,
      "360": 3,
      "361": 2,
      "362": 1,
      "363": 3,
      "365": 1,
      "366": 2,
      "367": 2,
      "368": 1,
      "369": 1,
      "370": 3,
      "371": 3,
      "375": 1,
      "377": 4,
      "379": 2,
      "380": 1,
      "381": 1,
      "382": 1,
      "383": 1,
      "384": 1,
      "385": 1,
      "392": 1,
      "395": 1,
      "397": 3,
      "398": 1,
      "400": 2,
      "402": 2,
      "403": 1,
      "404": 2,
      "405": 2,
      "406": 4,
      "407": 1,
      "408": 1,
      "409": 1,
      "410": 2,
      "413": 3,
      "415": 1,
      "416": 2,
      "418": 3,
      "419": 1,
      "422": 1,
      "424": 1,
      "425": 2,
      "427": 3,
      "428": 2,
      "430": 3,
      "431": 2,
      "432": 4,
      "433": 3,
      "434": 2,
      "435": 1,
      "436": 1,
      "437": 1,
      "438": 2,
      "439": 4,
      "440": 1,
      "441": 1,
      "444": 1,
      "447": 1,
      "449": 1,
      "453": 1,
      "455": 1,
      "456": 2,
      "457": 3,
      "458": 3,
      "459": 1,
      "460": 3,
      "461": 2,
      "463": 2,
      "464": 1,
      "465": 2,
      "467": 4,
      "468": 1,
      "471": 1,
      "472": 2,
      "476": 2,
      "478": 2,
      "480": 1,
      "481": 1,
      "482": 1,
      "484": 1,
      "485": 3,
      "486": 1,
      "488": 1,
      "489": 1,
      "493": 2,
      "495": 2,
      "501": 1,
      "502": 2,
      "503": 2,
      "507": 1,
      "508": 3,
      "509": 3,
      "510": 2,
      "512": 2,
      "514": 1,
      "517": 1,
      "520": 1,
      "523": 1,
      "527": 2,
      "528": 1,
      "529": 3,
      "532": 2,
      "538": 2,
      "544": 3,
      "545": 2,
      "551": 1,
      "554": 1,
      "559": 1,
      "560": 1,
      "561": 1,
      "563": 1,
      "564": 1,
      "565": 1,
      "570": 1,
      "572": 1,
      "577": 2,
      "578": 2,
      "583": 1,
      "586": 1,
      "589": 1,
      "592": 1,
      "594": 1,
      "607": 1,
      "608": 1,
      "609": 2,
      "610": 1,
      "611": 2,
      "612": 1,
      "613": 2,
      "614": 1,
      "615": 1,
      "616": 2,
      "618": 1,
      "619": 1,
      "623": 1,
      "626": 1,
      "629": 1,
      "630": 1,
      "632": 2,
      "633": 1,
      "634": 1,
      "635": 2,
      "636": 2,
      "637": 1,
      "639": 1,
      "641": 2,
      "643": 1,
      "644": 3,
      "645": 1,
      "647": 1,
      "648": 2,
      "650": 2,
      "651": 3,
      "652": 2,
      "653": 4,
      "654": 2,
      "657": 1,
      "661": 1,
      "663": 2,
      "664": 2,
      "665": 1,
      "666": 1,
      "667": 1,
      "668": 2,
      "669": 1,
      "670": 1,
      "672": 3,
      "674": 1,
      "675": 1,
      "676": 4,
      "677": 4,
      "678": 1,
      "679": 2,
      "681": 1,
      "682": 3,
      "684": 2,
      "686": 1,
      "687": 1,
      "688": 1,
      "689": 2,
      "691": 1,
      "692": 1,
      "693": 1,
      "694": 2,
      "695": 1,
      "696": 1,
      "697": 2,
      "698": 2,
      "699": 1,
      "700": 1,
      "702": 1,
      "703": 2,
      "704": 1,
      "705": 3,
      "706": 4,
      "708": 2,
      "709": 2,
      "710": 2,
      "711": 2,
      "713": 2,
      "715": 1,
      "716": 3,
      "718": 3,
      "721": 2,
      "729": 1,
      "734": 3,
      "735": 1,
      "742": 1,
      "744": 1,
      "746": 3,
      "749": 1,
      "750": 1,
      "751": 1,
      "752": 2,
      "753": 4,
      "755": 1,
      "756": 1,
      "757": 3,
      "758": 1,
      "759": 1,
      "760": 2,
      "762": 2,
      "764": 1,
      "766": 1,
      "768": 2,
      "769": 1,
      "770": 1,
      "771": 1,
      "772": 3,
      "775": 4,
      "778": 2,
      "780": 1,
      "782": 2,
      "783": 1,
      "784": 1,
      "786": 2,
      "787": 3,
      "788": 2,
      "789": 1,
      "790": 1,
      "791": 2,
      "795": 1,
      "797": 1,
      "799": 1,
      "802": 1,
      "804": 1,
      "807": 1,
      "808": 1,
      "809": 1,
      "812": 1,
      "813": 1,
      "814": 2,
      "816": 1,
      "819": 3,
      "820": 1,
      "821": 1,
      "824": 1,
      "825": 2,
      "826": 3,
      "827": 1,
      "828": 1,
      "829": 1,
      "830": 2,
      "831": 2,
      "832": 1,
      "833": 1,
      "835": 1,
      "836": 1,
      "837": 1,
      "838": 1,
      "840": 1,
      "845": 1,
      "846": 1,
      "847": 1,
      "848": 1,
      "849": 1,
      "850": 1,
      "852": 2,
      "854": 1,
      "855": 1,
      "858": 1,
      "861": 1,
      "865": 1,
      "866": 1,
      "871": 2,
      "872": 1,
      "874": 2,
      "877": 1,
      "878": 1,
      "879": 2,
      "880": 2,
      "881": 2,
      "883": 1,
      "884": 2,
      "885": 1,
      "886": 2,
      "889": 3,
      "890": 3,
      "892": 2,
      "893": 1,
      "895": 1,
      "897": 1,
      "898": 1,
      "899": 1,
      "900": 1,
      "901": 2,
      "904": 1,
      "905": 1,
      "906": 1,
      "908": 1,
      "909": 1,
      "910": 1,
      "911": 1,
      "912": 1,
      "913": 3,
      "914": 1,
      "915": 3,
      "916": 1,
      "917": 2,
      "918": 1,
      "920": 1,
      "922": 1,
      "923": 3,
      "924": 1,
      "925": 1,
      "928": 1,
      "931": 4,
      "932": 2,
      "934": 2,
      "936": 1,
      "937": 2,
      "939": 2,
      "942": 1,
      "943": 1,
      "945": 2,
      "946": 1,
      "949": 1,
      "950": 3,
      "952": 2,
      "953": 3,
      "954": 3,
      "955": 3,
      "956": 1,
      "958": 1,
      "959": 2,
      "961": 1,
      "962": 1,
      "965": 2,
      "966": 1,
      "968": 2,
      "969": 2,
      "970": 2,
      "972": 2,
      "973": 3,
      "974": 1,
      "975": 1,
      "976": 4,
      "977": 4,
      "979": 2,
      "981": 2,
      "982": 2,
      "983": 1,
      "984": 8,
      "987": 1,
      "988": 3,
      "989": 6,
      "990": 2,
      "991": 2,
      "992": 3,
      "993": 1,
      "995": 2,
      "996": 1,
      "998": 3,
      "1001": 1,
      "1002": 1,
      "1003": 1,
      "1004": 1,
      "1006": 1,
      "1007": 1,
      "1008": 4,
      "1010": 1,
      "1011": 3,
      "1013": 1,
      "1014": 1,
      "1015": 1,
      "1016": 1,
      "1017": 1,
      "1021": 1,
      "1023": 1,
      "1025": 1,
      "1027": 1,
      "1029": 1,
      "1031": 1,
      "1032": 97210
   },
   "wasClean": true,
   "wasCloseHandshakeTimeout": false,
   "wasNotCleanReason": null,
   "wasOpenHandshakeTimeout": false,
   "wasServerConnectionDropTimeout": false,
   "wirelog": [
      [
         "TO",
         [
            338,
            "474554202f20485454502f312e310d0a557365722d4167656e743a204175746f6261686e5465737453756974652f302e382e312d302e31302e390d0a486f7374 ..."
         ],
         false
      ],
      [
         "RO",
         [
            238,
            "485454502f312e31203130312057656220536f636b65742050726f746f636f6c2048616e647368616b650d0a557067726164653a20576562536f636b65740d0a ..."
         ]
      ],
      [
         "WLM",
         false
      ],
      [
         "TI",
         480
      ],
      [
         "WLM",
         true
      ],
      [
         "TF",
         [
            2,
            "0x03e8"
         ],
         8,
         true,
         0,
         "6ca87688",
         null,
         null,
         false
      ],
      [
         "TO",
         [
            8,
            "88826ca876886f40"
         ],
         false
      ],
      [
         "RO",
         [
            4,
            "880203e8"
         ]
      ],
      [
         "RF",
         [
            2,
            "0x03e8"
         ],
         8,
         true,
         0,
         false,
         null
      ]
   ]
}